Metadata-Version: 2.1
Name: dsbot
Version: 0.0.9
Summary: Chatbot framework ...
Home-page: http://pypi.python.org/pypi/dsbot/
Author: Jefry
Author-email: jefry.sastre@gmail.com
License: LICENSE.txt
Platform: UNKNOWN
Requires-Dist: matplotlib (==3.3.1)
Requires-Dist: nltk (==3.5)
Requires-Dist: numpy (==1.18.5)
Requires-Dist: TPOT (==0.11.5)
Requires-Dist: pyod (==0.8.2)
Requires-Dist: tqdm (==4.48.2)
Requires-Dist: h5py (==2.10.0)
Requires-Dist: tensorflow (==2.3.0)
Requires-Dist: scipy (==1.4.1)
Requires-Dist: scikit-learn (==0.23.2)
Requires-Dist: requests (==2.24.0)
Requires-Dist: regex (==2020.7.14)
Requires-Dist: pandas (==1.1.1)
Requires-Dist: Keras (==2.4.3)
Requires-Dist: sentence-transformers (==0.3.8)
